RAM/rtl/top.v
module ram16x8 (
	input wire clk,
	input wire rst_n,
	input wire ce,
	input wire rd_en,
	input wire wr_en,
	input wire [3:0] addr, // Access address (4 bits for the 16 adresses)
	input wire [7:0] data_in,
	output reg [7:0] data_out,
	output reg valid
);

reg [7:0] ram [15:0];
reg [7:0] read_data;

always @(posedge clk or negedge rst_n) begin
	if(!rst_n) begin
		data_out <= 8'h00;
		valid <= 1'b0;
	end else if (ce) begin
		if (wr_en) begin
			ram[addr] <= data_in;
			valid <= 1'b0;
		end else if (rd_en) begin
			read_data <= ram[addr];
			valid <= 1'b1;
		end else begin
			valid <= 1'b0;
		end
	end else begin
		valid <= 1'b0;
	end
end

always @(*) begin
	if (ce && rd_en) begin
		data_out <= read_data;
	end else begin
		data_out <= 8'h00;
	end
end
endmodule

RAM/tb/test_bench.v
`timescale 1ns/1ps
module test_bench;
	reg clk, rst_n, ce, rd_en, wr_en;
	reg [3:0] addr;
	reg [7:0] data_in;
	wire [7:0] data_out;
	wire valid;

	integer i;

	ram16x8 dut(
		.clk(clk),
		.rst_n(rst_n),
		.ce(ce),
		.rd_en(rd_en),
		.wr_en(wr_en),
		.addr(addr),
		.data_in(data_in),
		.data_out(data_out),
		.valid(valid)
	);

	initial begin
		clk = 0;
		forever #5 clk = ~clk; 
	end

	task verify;
		input [7:0] exp_data_out;
		input exp_valid;
		begin
			$display("At time: %t, rst_n = 1'b%b, ce = 1'b%b, rd_en = 1'b%b, wr_en = 1'b%b, addr = 4'b%b, data_in = 8'b%b",$time, rst_n, ce, rd_en, wr_en, addr, data_in);
			if (data_out == exp_data_out && valid == exp_valid) begin
				$display("-----------------------------------------------------------------------------------------------------------------");
				$display("PASSED: Expected data_out: 8'b%b, Got data_out: 8'b%b, Expectd valid: 1'b%b, Got valid: 1'b%b", exp_data_out, data_out, exp_valid, valid);
				$display("-----------------------------------------------------------------------------------------------------------------");
			end else begin
				$display("-----------------------------------------------------------------------------------------------------------------");
				$display("FAILED: Expected data_out: 8'b%b, Got data_out: 8'b%b, Expectd valid: 1'b%b, Got valid: 1'b%b", exp_data_out, data_out, exp_valid, valid);
				$display("-----------------------------------------------------------------------------------------------------------------");
			end
		end
	endtask

	initial begin
		$dumpfile("test_bench.vcd");
		$dumpvars(0, test_bench);

		$display("-----------------------------------------------------------------------------------------------------------------");
		$display("-------------------------------------TESTBENCH FOR RAM 16X8------------------------------------------------------");
		$display("-----------------------------------------------------------------------------------------------------------------");

		rst_n = 0;
		ce = 0;
		rd_en = 0;
		wr_en = 0;
		addr = 4'b0000;
		data_in = 8'hff;
		@(posedge clk);
		verify(0,0);

		rst_n = 1;
		ce = 0;
		rd_en = 1;
		wr_en = 0;
		addr = 4'h5;
		data_in = 8'haa;
		@(posedge clk);
		verify(0,0);

		ce = 1;
		@(posedge clk);

		for (i = 0; i < 16; i = i + 1) begin
			rd_en = 0;
			wr_en = 1;
			addr = i;
			data_in = $random % 256;
			@(posedge clk);
			verify(0,0);

			rd_en = 1;
			wr_en = 0;
			addr = i;
			@(posedge clk);
			verify(data_in, 1);
		end

		$display("------------------------------------COMPLETED TESTBENCH FOR RAM 16X8 --------------------------------------------");
		#100;
		$finish;
	end
endmodule

RAM/sim/test_bench.vcd
$date
	Sun Jan 12 10:45:48 2025
$end
$version
	Icarus Verilog
$end
$timescale
	1ps
$end
$scope module test_bench $end
$var wire 1 ! valid $end
$var wire 8 " data_out [7:0] $end
$var reg 4 # addr [3:0] $end
$var reg 1 $ ce $end
$var reg 1 % clk $end
$var reg 8 & data_in [7:0] $end
$var reg 1 ' rd_en $end
$var reg 1 ( rst_n $end
$var reg 1 ) wr_en $end
$var integer 32 * i [31:0] $end
$scope module dut $end
$var wire 4 + addr [3:0] $end
$var wire 1 $ ce $end
$var wire 1 % clk $end
$var wire 8 , data_in [7:0] $end
$var wire 1 ' rd_en $end
$var wire 1 ( rst_n $end
$var wire 1 ) wr_en $end
$var reg 8 - data_out [7:0] $end
$var reg 8 . read_data [7:0] $end
$var reg 1 ! valid $end
$upscope $end
$scope task verify $end
$var reg 8 / exp_data_out [7:0] $end
$var reg 1 0 exp_valid $end
$upscope $end
$upscope $end
$enddefinitions $end
$comment Show the parameter values. $end
$dumpall
$end
#0
$dumpvars
x0
bx /
bx .
b0 -
b11111111 ,
b0 +
bx *
0)
0(
0'
b11111111 &
0%
0$
b0 #
b0 "
0!
$end
#5000
b10101010 &
b10101010 ,
b101 #
b101 +
1'
1(
00
b0 /
1%
#10000
0%
#15000
bx "
bx -
1!
1$
1%
#20000
0%
#25000
b0 "
b0 -
0!
b100100 &
b100100 ,
b0 #
b0 +
1)
0'
b0 *
1%
#30000
0%
#35000
b100100 "
b100100 -
1!
b100100 .
0)
1'
1%
#40000
0%
#45000
b0 "
b0 -
0!
b10000001 &
b10000001 ,
b1 #
b1 +
1)
0'
b1 *
10
b100100 /
1%
#50000
0%
#55000
b10000001 "
b10000001 -
1!
b10000001 .
0)
1'
00
b0 /
1%
#60000
0%
#65000
b0 "
b0 -
0!
b1001 &
b1001 ,
b10 #
b10 +
1)
0'
b10 *
10
b10000001 /
1%
#70000
0%
#75000
b1001 "
b1001 -
1!
b1001 .
0)
1'
00
b0 /
1%
#80000
0%
#85000
b0 "
b0 -
0!
b1100011 &
b1100011 ,
b11 #
b11 +
1)
0'
b11 *
10
b1001 /
1%
#90000
0%
#95000
b1100011 "
b1100011 -
1!
b1100011 .
0)
1'
00
b0 /
1%
#100000
0%
#105000
b0 "
b0 -
0!
b1101 &
b1101 ,
b100 #
b100 +
1)
0'
b100 *
10
b1100011 /
1%
#110000
0%
#115000
b1101 "
b1101 -
1!
b1101 .
0)
1'
00
b0 /
1%
#120000
0%
#125000
b0 "
b0 -
0!
b10001101 &
b10001101 ,
b101 #
b101 +
1)
0'
b101 *
10
b1101 /
1%
#130000
0%
#135000
b10001101 "
b10001101 -
1!
b10001101 .
0)
1'
00
b0 /
1%
#140000
0%
#145000
b0 "
b0 -
0!
b1100101 &
b1100101 ,
b110 #
b110 +
1)
0'
b110 *
10
b10001101 /
1%
#150000
0%
#155000
b1100101 "
b1100101 -
1!
b1100101 .
0)
1'
00
b0 /
1%
#160000
0%
#165000
b0 "
b0 -
0!
b10010 &
b10010 ,
b111 #
b111 +
1)
0'
b111 *
10
b1100101 /
1%
#170000
0%
#175000
b10010 "
b10010 -
1!
b10010 .
0)
1'
00
b0 /
1%
#180000
0%
#185000
b0 "
b0 -
0!
b1 &
b1 ,
b1000 #
b1000 +
1)
0'
b1000 *
10
b10010 /
1%
#190000
0%
#195000
b1 "
b1 -
1!
b1 .
0)
1'
00
b0 /
1%
#200000
0%
#205000
b0 "
b0 -
0!
b1101 &
b1101 ,
b1001 #
b1001 +
1)
0'
b1001 *
10
b1 /
1%
#210000
0%
#215000
b1101 "
b1101 -
1!
b1101 .
0)
1'
00
b0 /
1%
#220000
0%
#225000
b0 "
b0 -
0!
b1110110 &
b1110110 ,
b1010 #
b1010 +
1)
0'
b1010 *
10
b1101 /
1%
#230000
0%
#235000
b1110110 "
b1110110 -
1!
b1110110 .
0)
1'
00
b0 /
1%
#240000
0%
#245000
b0 "
b0 -
0!
b111101 &
b111101 ,
b1011 #
b1011 +
1)
0'
b1011 *
10
b1110110 /
1%
#250000
0%
#255000
b111101 "
b111101 -
1!
b111101 .
0)
1'
00
b0 /
1%
#260000
0%
#265000
b0 "
b0 -
0!
b11101101 &
b11101101 ,
b1100 #
b1100 +
1)
0'
b1100 *
10
b111101 /
1%
#270000
0%
#275000
b11101101 "
b11101101 -
1!
b11101101 .
0)
1'
00
b0 /
1%
#280000
0%
#285000
b0 "
b0 -
0!
b10001100 &
b10001100 ,
b1101 #
b1101 +
1)
0'
b1101 *
10
b11101101 /
1%
#290000
0%
#295000
b10001100 "
b10001100 -
1!
b10001100 .
0)
1'
00
b0 /
1%
#300000
0%
#305000
b0 "
b0 -
0!
b11111001 &
b11111001 ,
b1110 #
b1110 +
1)
0'
b1110 *
10
b10001100 /
1%
#310000
0%
#315000
b11111001 "
b11111001 -
1!
b11111001 .
0)
1'
00
b0 /
1%
#320000
0%
#325000
b0 "
b0 -
0!
b11000110 &
b11000110 ,
b1111 #
b1111 +
1)
0'
b1111 *
10
b11111001 /
1%
#330000
0%
#335000
b11000110 "
b11000110 -
1!
b11000110 .
0)
1'
00
b0 /
1%
#340000
0%
#345000
b10000 *
10
b11000110 /
1%
